{
  "timestamp": "2026-01-31T04:40:42.858Z",
  "description": "Proposed Unit 8 Relational Data",
  "skills": [
    {
      "id": "washer_method_inner_outer_radius",
      "name": "washer_method_inner_outer_radius",
      "unit": "Applications_of_Integration"
    },
    {
      "id": "axis_as_reference_radius",
      "name": "axis_as_reference_radius",
      "unit": "Applications_of_Integration"
    },
    {
      "id": "average_value_formula",
      "name": "average_value_formula",
      "unit": "Applications_of_Integration"
    },
    {
      "id": "average_value_interpretation",
      "name": "average_value_interpretation",
      "unit": "Applications_of_Integration"
    },
    {
      "id": "area_multiple_intersections_split",
      "name": "area_multiple_intersections_split",
      "unit": "Applications_of_Integration"
    },
    {
      "id": "area_top_minus_bottom_or_right_minus_left",
      "name": "area_top_minus_bottom_or_right_minus_left",
      "unit": "Applications_of_Integration"
    },
    {
      "id": "total_distance_vs_displacement",
      "name": "total_distance_vs_displacement",
      "unit": "Applications_of_Integration"
    },
    {
      "id": "motion_displacement_from_velocity",
      "name": "motion_displacement_from_velocity",
      "unit": "Applications_of_Integration"
    },
    {
      "id": "units_interpretation_in_applications",
      "name": "units_interpretation_in_applications",
      "unit": "Applications_of_Integration"
    },
    {
      "id": "area_between_curves_dy_setup",
      "name": "area_between_curves_dy_setup",
      "unit": "Applications_of_Integration"
    },
    {
      "id": "arc_length_integrand_build",
      "name": "arc_length_integrand_build",
      "unit": "Applications_of_Integration"
    },
    {
      "id": "arc_length_derivative_needed",
      "name": "arc_length_derivative_needed",
      "unit": "Applications_of_Integration"
    },
    {
      "id": "accumulation_from_rate",
      "name": "accumulation_from_rate",
      "unit": "Applications_of_Integration"
    },
    {
      "id": "bounds_from_context",
      "name": "bounds_from_context",
      "unit": "Applications_of_Integration"
    },
    {
      "id": "washer_method_evaluation",
      "name": "washer_method_evaluation",
      "unit": "Applications_of_Integration"
    },
    {
      "id": "washer_method_setup",
      "name": "washer_method_setup",
      "unit": "Applications_of_Integration"
    },
    {
      "id": "washer_shift_radius_adjustment",
      "name": "washer_shift_radius_adjustment",
      "unit": "Applications_of_Integration"
    },
    {
      "id": "volume_revolution_about_shifted_axis",
      "name": "volume_revolution_about_shifted_axis",
      "unit": "Applications_of_Integration"
    },
    {
      "id": "radius_distance_to_axis",
      "name": "radius_distance_to_axis",
      "unit": "Applications_of_Integration"
    },
    {
      "id": "net_change_vs_total_change_context",
      "name": "net_change_vs_total_change_context",
      "unit": "Applications_of_Integration"
    },
    {
      "id": "disk_method_setup",
      "name": "disk_method_setup",
      "unit": "Applications_of_Integration"
    },
    {
      "id": "disk_method_radius_expression",
      "name": "disk_method_radius_expression",
      "unit": "Applications_of_Integration"
    },
    {
      "id": "area_between_curves_dx_setup",
      "name": "area_between_curves_dx_setup",
      "unit": "Applications_of_Integration"
    },
    {
      "id": "disk_method_evaluation",
      "name": "disk_method_evaluation",
      "unit": "Applications_of_Integration"
    },
    {
      "id": "disk_method_bounds",
      "name": "disk_method_bounds",
      "unit": "Applications_of_Integration"
    },
    {
      "id": "axis_shift_handling",
      "name": "axis_shift_handling",
      "unit": "Applications_of_Integration"
    },
    {
      "id": "cross_section_semicircle_area",
      "name": "cross_section_semicircle_area",
      "unit": "Applications_of_Integration"
    },
    {
      "id": "volume_cross_sections_setup",
      "name": "volume_cross_sections_setup",
      "unit": "Applications_of_Integration"
    },
    {
      "id": "average_value_from_graph_or_table",
      "name": "average_value_from_graph_or_table",
      "unit": "Applications_of_Integration"
    },
    {
      "id": "motion_velocity_from_acceleration_with_initial",
      "name": "motion_velocity_from_acceleration_with_initial",
      "unit": "Applications_of_Integration"
    },
    {
      "id": "motion_position_with_initial_condition",
      "name": "motion_position_with_initial_condition",
      "unit": "Applications_of_Integration"
    },
    {
      "id": "disk_shift_radius_adjustment",
      "name": "disk_shift_radius_adjustment",
      "unit": "Applications_of_Integration"
    },
    {
      "id": "cross_section_rectangle_area",
      "name": "cross_section_rectangle_area",
      "unit": "Applications_of_Integration"
    },
    {
      "id": "cross_section_triangle_area",
      "name": "cross_section_triangle_area",
      "unit": "Applications_of_Integration"
    },
    {
      "id": "solve_intersections_for_bounds",
      "name": "solve_intersections_for_bounds",
      "unit": "Applications_of_Integration"
    },
    {
      "id": "integration_modeling_from_context",
      "name": "integration_modeling_from_context",
      "unit": "Applications_of_Integration"
    },
    {
      "id": "arc_length_derivative_and_sqrt",
      "name": "arc_length_derivative_and_sqrt",
      "unit": "Applications_of_Integration"
    },
    {
      "id": "arc_length_formula",
      "name": "arc_length_formula",
      "unit": "Applications_of_Integration"
    },
    {
      "id": "numerical_approx_trapezoid_volume",
      "name": "numerical_approx_trapezoid_volume",
      "unit": "Applications_of_Integration"
    },
    {
      "id": "choose_dx_or_dy_strategy_volume",
      "name": "choose_dx_or_dy_strategy_volume",
      "unit": "Applications_of_Integration"
    },
    {
      "id": "cross_section_area_function",
      "name": "cross_section_area_function",
      "unit": "Applications_of_Integration"
    },
    {
      "id": "volume_disk_method_basic",
      "name": "volume_disk_method_basic",
      "unit": "Applications_of_Integration"
    },
    {
      "id": "volume_revolution_about_x_or_y",
      "name": "volume_revolution_about_x_or_y",
      "unit": "Applications_of_Integration"
    },
    {
      "id": "arc_length_formula_setup",
      "name": "arc_length_formula_setup",
      "unit": "Applications_of_Integration"
    },
    {
      "id": "arc_length_units_interpretation",
      "name": "arc_length_units_interpretation",
      "unit": "Applications_of_Integration"
    },
    {
      "id": "distance_vs_displacement",
      "name": "distance_vs_displacement",
      "unit": "Applications_of_Integration"
    },
    {
      "id": "choose_dx_or_dy_strategy_area",
      "name": "choose_dx_or_dy_strategy_area",
      "unit": "Applications_of_Integration"
    },
    {
      "id": "cross_sections_square",
      "name": "cross_sections_square",
      "unit": "Applications_of_Integration"
    },
    {
      "id": "absolute_value_in_distance",
      "name": "absolute_value_in_distance",
      "unit": "Applications_of_Integration"
    },
    {
      "id": "method_selection_disk_vs_washer",
      "name": "method_selection_disk_vs_washer",
      "unit": "Applications_of_Integration"
    },
    {
      "id": "cross_section_square_area",
      "name": "cross_section_square_area",
      "unit": "Applications_of_Integration"
    },
    {
      "id": "distance_from_velocity_graph",
      "name": "distance_from_velocity_graph",
      "unit": "Applications_of_Integration"
    },
    {
      "id": "cross_sections_semicircle",
      "name": "cross_sections_semicircle",
      "unit": "Applications_of_Integration"
    },
    {
      "id": "volume_integral_evaluation",
      "name": "volume_integral_evaluation",
      "unit": "Applications_of_Integration"
    }
  ],
  "error_tags": [
    {
      "id": "wrong_radius_expression",
      "name": "wrong_radius_expression"
    },
    {
      "id": "inner_outer_swapped",
      "name": "inner_outer_swapped"
    },
    {
      "id": "shift_not_applied",
      "name": "shift_not_applied"
    },
    {
      "id": "avg_value_wrong_bounds",
      "name": "avg_value_wrong_bounds"
    },
    {
      "id": "avg_value_wrong_interval_length",
      "name": "avg_value_wrong_interval_length"
    },
    {
      "id": "algebra_simplification_error",
      "name": "algebra_simplification_error"
    },
    {
      "id": "area_missing_split_interval",
      "name": "area_missing_split_interval"
    },
    {
      "id": "area_missing_abs_value",
      "name": "area_missing_abs_value"
    },
    {
      "id": "area_wrong_top_minus_bottom",
      "name": "area_wrong_top_minus_bottom"
    },
    {
      "id": "motion_displacement_distance_confusion",
      "name": "motion_displacement_distance_confusion"
    },
    {
      "id": "motion_sign_mistake",
      "name": "motion_sign_mistake"
    },
    {
      "id": "motion_units_mismatch",
      "name": "motion_units_mismatch"
    },
    {
      "id": "accumulation_units_mismatch",
      "name": "accumulation_units_mismatch"
    },
    {
      "id": "area_wrong_dx_dy_choice",
      "name": "area_wrong_dx_dy_choice"
    },
    {
      "id": "arc_length_missing_sqrt",
      "name": "arc_length_missing_sqrt"
    },
    {
      "id": "arc_length_missing_square_on_derivative",
      "name": "arc_length_missing_square_on_derivative"
    },
    {
      "id": "derivative_error",
      "name": "derivative_error"
    },
    {
      "id": "accumulation_bounds_misread_context",
      "name": "accumulation_bounds_misread_context"
    },
    {
      "id": "missing_pi_factor",
      "name": "missing_pi_factor"
    },
    {
      "id": "squared_radius_missing",
      "name": "squared_radius_missing"
    },
    {
      "id": "volume_wrong_axis_distance_shift",
      "name": "volume_wrong_axis_distance_shift"
    },
    {
      "id": "volume_washer_radii_reversed",
      "name": "volume_washer_radii_reversed"
    },
    {
      "id": "volume_forget_square_radius",
      "name": "volume_forget_square_radius"
    },
    {
      "id": "accumulation_net_vs_total_confusion",
      "name": "accumulation_net_vs_total_confusion"
    },
    {
      "id": "avg_value_missing_divide_by_interval",
      "name": "avg_value_missing_divide_by_interval"
    },
    {
      "id": "washer_vs_disk_confusion",
      "name": "washer_vs_disk_confusion"
    },
    {
      "id": "area_intersections_incorrect",
      "name": "area_intersections_incorrect"
    },
    {
      "id": "rounding_too_early",
      "name": "rounding_too_early"
    },
    {
      "id": "wrong_bounds",
      "name": "wrong_bounds"
    },
    {
      "id": "wrong_cross_section_area_formula",
      "name": "wrong_cross_section_area_formula"
    },
    {
      "id": "bounds_from_context",
      "name": "bounds_from_context"
    },
    {
      "id": "motion_forget_initial_condition",
      "name": "motion_forget_initial_condition"
    },
    {
      "id": "avg_value_integrand_misread",
      "name": "avg_value_integrand_misread"
    },
    {
      "id": "accumulation_wrong_rate_variable",
      "name": "accumulation_wrong_rate_variable"
    },
    {
      "id": "arc_length_missing_sqrt_structure",
      "name": "arc_length_missing_sqrt_structure"
    },
    {
      "id": "arc_length_wrong_derivative",
      "name": "arc_length_wrong_derivative"
    },
    {
      "id": "trapezoid_weight_error",
      "name": "trapezoid_weight_error"
    },
    {
      "id": "wrong_dx_dy_choice_volume",
      "name": "wrong_dx_dy_choice_volume"
    },
    {
      "id": "cross_section_side_length_misread",
      "name": "cross_section_side_length_misread"
    },
    {
      "id": "cross_section_wrong_area_formula",
      "name": "cross_section_wrong_area_formula"
    },
    {
      "id": "volume_missing_pi_factor",
      "name": "volume_missing_pi_factor"
    },
    {
      "id": "volume_wrong_limits",
      "name": "volume_wrong_limits"
    },
    {
      "id": "volume_radius_height_swapped",
      "name": "volume_radius_height_swapped"
    },
    {
      "id": "units_mismatch_distance",
      "name": "units_mismatch_distance"
    },
    {
      "id": "distance_equals_displacement_mistake",
      "name": "distance_equals_displacement_mistake"
    },
    {
      "id": "formula_context_confusion",
      "name": "formula_context_confusion"
    },
    {
      "id": "missing_absolute_value",
      "name": "missing_absolute_value"
    },
    {
      "id": "signed_area_misread",
      "name": "signed_area_misread"
    },
    {
      "id": "arc_length_wrong_bounds",
      "name": "arc_length_wrong_bounds"
    },
    {
      "id": "piecewise_interval_missed",
      "name": "piecewise_interval_missed"
    }
  ],
  "question_skills": [
    {
      "question_id": "040b5ab8-a45a-4b95-b83a-4a33f2cc71a1",
      "skill_id": "washer_method_inner_outer_radius"
    },
    {
      "question_id": "040b5ab8-a45a-4b95-b83a-4a33f2cc71a1",
      "skill_id": "axis_as_reference_radius"
    },
    {
      "question_id": "09004717-b58d-4f9e-868a-bf58da087a1e",
      "skill_id": "average_value_formula"
    },
    {
      "question_id": "09004717-b58d-4f9e-868a-bf58da087a1e",
      "skill_id": "average_value_interpretation"
    },
    {
      "question_id": "0c0a3f5c-4397-45b3-913b-39f6806bd9b4",
      "skill_id": "area_multiple_intersections_split"
    },
    {
      "question_id": "0c0a3f5c-4397-45b3-913b-39f6806bd9b4",
      "skill_id": "area_top_minus_bottom_or_right_minus_left"
    },
    {
      "question_id": "0d7a6634-ab75-4860-ba8b-2cf78455ec41",
      "skill_id": "total_distance_vs_displacement"
    },
    {
      "question_id": "0d7a6634-ab75-4860-ba8b-2cf78455ec41",
      "skill_id": "motion_displacement_from_velocity"
    },
    {
      "question_id": "0deaca7b-8a3f-4cb5-86a9-fbfa269384b1",
      "skill_id": "units_interpretation_in_applications"
    },
    {
      "question_id": "0deaca7b-8a3f-4cb5-86a9-fbfa269384b1",
      "skill_id": "motion_displacement_from_velocity"
    },
    {
      "question_id": "0f167af7-aab5-43ed-9161-969d1f3d923d",
      "skill_id": "area_between_curves_dy_setup"
    },
    {
      "question_id": "0f167af7-aab5-43ed-9161-969d1f3d923d",
      "skill_id": "area_top_minus_bottom_or_right_minus_left"
    },
    {
      "question_id": "0f8a7302-5790-4b3d-8ce3-46ad6264a000",
      "skill_id": "arc_length_integrand_build"
    },
    {
      "question_id": "0f8a7302-5790-4b3d-8ce3-46ad6264a000",
      "skill_id": "arc_length_derivative_needed"
    },
    {
      "question_id": "10029da7-2468-440b-929c-92b7c3b8ace2",
      "skill_id": "accumulation_from_rate"
    },
    {
      "question_id": "10029da7-2468-440b-929c-92b7c3b8ace2",
      "skill_id": "bounds_from_context"
    },
    {
      "question_id": "1075384f-803f-4bc5-b4a8-cc3eaa45407b",
      "skill_id": "washer_method_evaluation"
    },
    {
      "question_id": "1075384f-803f-4bc5-b4a8-cc3eaa45407b",
      "skill_id": "washer_method_setup"
    },
    {
      "question_id": "1426bef5-bba5-42ff-bb81-49214c4fa0e5",
      "skill_id": "washer_shift_radius_adjustment"
    },
    {
      "question_id": "1426bef5-bba5-42ff-bb81-49214c4fa0e5",
      "skill_id": "washer_method_setup"
    },
    {
      "question_id": "17555163-7087-48a1-b2c9-4dde865d05ec",
      "skill_id": "volume_revolution_about_shifted_axis"
    },
    {
      "question_id": "17555163-7087-48a1-b2c9-4dde865d05ec",
      "skill_id": "radius_distance_to_axis"
    },
    {
      "question_id": "189a2d07-8793-45ff-a936-b4fe913d8e43",
      "skill_id": "net_change_vs_total_change_context"
    },
    {
      "question_id": "189a2d07-8793-45ff-a936-b4fe913d8e43",
      "skill_id": "accumulation_from_rate"
    },
    {
      "question_id": "1b426fb4-0188-4cb3-8bde-df050cd920a7",
      "skill_id": "average_value_interpretation"
    },
    {
      "question_id": "1b426fb4-0188-4cb3-8bde-df050cd920a7",
      "skill_id": "units_interpretation_in_applications"
    },
    {
      "question_id": "20276c63-b20b-415b-871c-7f1ab25ca8b1",
      "skill_id": "disk_method_setup"
    },
    {
      "question_id": "20276c63-b20b-415b-871c-7f1ab25ca8b1",
      "skill_id": "disk_method_radius_expression"
    },
    {
      "question_id": "21f3b314-4620-45b7-b08c-522b1b1b6b3d",
      "skill_id": "area_between_curves_dy_setup"
    },
    {
      "question_id": "21f3b314-4620-45b7-b08c-522b1b1b6b3d",
      "skill_id": "area_top_minus_bottom_or_right_minus_left"
    },
    {
      "question_id": "243a4a21-b161-4357-9fe7-c0288508f525",
      "skill_id": "area_top_minus_bottom_or_right_minus_left"
    },
    {
      "question_id": "243a4a21-b161-4357-9fe7-c0288508f525",
      "skill_id": "area_between_curves_dx_setup"
    },
    {
      "question_id": "2abf3b03-3490-4e15-a969-92326903d26f",
      "skill_id": "accumulation_from_rate"
    },
    {
      "question_id": "2abf3b03-3490-4e15-a969-92326903d26f",
      "skill_id": "bounds_from_context"
    },
    {
      "question_id": "2c20fb9c-e5de-43e8-82b3-75d6cf47aa8c",
      "skill_id": "disk_method_setup"
    },
    {
      "question_id": "2c20fb9c-e5de-43e8-82b3-75d6cf47aa8c",
      "skill_id": "disk_method_evaluation"
    },
    {
      "question_id": "2c689f9b-7fc2-470a-9237-5b69245cfcba",
      "skill_id": "disk_method_setup"
    },
    {
      "question_id": "2c689f9b-7fc2-470a-9237-5b69245cfcba",
      "skill_id": "disk_method_bounds"
    },
    {
      "question_id": "2ebdfdda-162a-4aea-887f-57dd3f9b4fb3",
      "skill_id": "washer_method_evaluation"
    },
    {
      "question_id": "2ebdfdda-162a-4aea-887f-57dd3f9b4fb3",
      "skill_id": "washer_shift_radius_adjustment"
    },
    {
      "question_id": "2f1454f2-8e5d-4a7e-beb6-709f5fab1daa",
      "skill_id": "axis_shift_handling"
    },
    {
      "question_id": "2f1454f2-8e5d-4a7e-beb6-709f5fab1daa",
      "skill_id": "washer_shift_radius_adjustment"
    },
    {
      "question_id": "344ef49b-3cfb-49ea-bbab-99057779bd4f",
      "skill_id": "washer_method_setup"
    },
    {
      "question_id": "344ef49b-3cfb-49ea-bbab-99057779bd4f",
      "skill_id": "washer_method_inner_outer_radius"
    },
    {
      "question_id": "352c7ca7-544c-4f9e-992f-d2b4afc24e9b",
      "skill_id": "net_change_vs_total_change_context"
    },
    {
      "question_id": "352c7ca7-544c-4f9e-992f-d2b4afc24e9b",
      "skill_id": "accumulation_from_rate"
    },
    {
      "question_id": "37c1ed76-a81c-4b6b-88f6-abe75f39ee73",
      "skill_id": "cross_section_semicircle_area"
    },
    {
      "question_id": "37c1ed76-a81c-4b6b-88f6-abe75f39ee73",
      "skill_id": "volume_cross_sections_setup"
    },
    {
      "question_id": "382aa404-ba83-4409-b250-937e085ae233",
      "skill_id": "average_value_from_graph_or_table"
    },
    {
      "question_id": "382aa404-ba83-4409-b250-937e085ae233",
      "skill_id": "average_value_formula"
    },
    {
      "question_id": "400d0056-1257-426f-aadc-581d77a45a57",
      "skill_id": "motion_velocity_from_acceleration_with_initial"
    },
    {
      "question_id": "400d0056-1257-426f-aadc-581d77a45a57",
      "skill_id": "bounds_from_context"
    },
    {
      "question_id": "41d4eb24-965a-48b2-bcd3-36df3f25eb18",
      "skill_id": "motion_position_with_initial_condition"
    },
    {
      "question_id": "41d4eb24-965a-48b2-bcd3-36df3f25eb18",
      "skill_id": "motion_displacement_from_velocity"
    },
    {
      "question_id": "44e18621-fe3a-4a50-85f5-a24af76806d9",
      "skill_id": "accumulation_from_rate"
    },
    {
      "question_id": "44e18621-fe3a-4a50-85f5-a24af76806d9",
      "skill_id": "units_interpretation_in_applications"
    },
    {
      "question_id": "48c81e29-b753-405e-a4ef-3928781a602e",
      "skill_id": "average_value_formula"
    },
    {
      "question_id": "48c81e29-b753-405e-a4ef-3928781a602e",
      "skill_id": "bounds_from_context"
    },
    {
      "question_id": "57a7fa38-095b-4444-a828-7d47de27a4c3",
      "skill_id": "area_between_curves_dx_setup"
    },
    {
      "question_id": "57a7fa38-095b-4444-a828-7d47de27a4c3",
      "skill_id": "area_top_minus_bottom_or_right_minus_left"
    },
    {
      "question_id": "5ce67712-d4ec-4720-aaae-f070ae630b07",
      "skill_id": "disk_shift_radius_adjustment"
    },
    {
      "question_id": "5ce67712-d4ec-4720-aaae-f070ae630b07",
      "skill_id": "disk_method_evaluation"
    },
    {
      "question_id": "5d33cace-d80f-4c93-9d38-b3c8b5f3cb5c",
      "skill_id": "area_multiple_intersections_split"
    },
    {
      "question_id": "5d33cace-d80f-4c93-9d38-b3c8b5f3cb5c",
      "skill_id": "area_top_minus_bottom_or_right_minus_left"
    },
    {
      "question_id": "60aea1df-a460-485b-8013-12ddffdcf88c",
      "skill_id": "average_value_formula"
    },
    {
      "question_id": "60aea1df-a460-485b-8013-12ddffdcf88c",
      "skill_id": "bounds_from_context"
    },
    {
      "question_id": "65f2104c-b6a9-4779-8ba7-c0b69ff96576",
      "skill_id": "area_between_curves_dy_setup"
    },
    {
      "question_id": "65f2104c-b6a9-4779-8ba7-c0b69ff96576",
      "skill_id": "area_top_minus_bottom_or_right_minus_left"
    },
    {
      "question_id": "6838d020-97d2-499b-abda-a204e72b6efd",
      "skill_id": "average_value_from_graph_or_table"
    },
    {
      "question_id": "6838d020-97d2-499b-abda-a204e72b6efd",
      "skill_id": "average_value_formula"
    },
    {
      "question_id": "69a48f75-ec8c-4aa3-8603-29a32c45e72e",
      "skill_id": "cross_section_rectangle_area"
    },
    {
      "question_id": "69a48f75-ec8c-4aa3-8603-29a32c45e72e",
      "skill_id": "volume_cross_sections_setup"
    },
    {
      "question_id": "6a3cd460-a07e-45f6-86ff-c7f8272cde07",
      "skill_id": "cross_section_triangle_area"
    },
    {
      "question_id": "6a3cd460-a07e-45f6-86ff-c7f8272cde07",
      "skill_id": "volume_cross_sections_setup"
    },
    {
      "question_id": "6b7bb29a-de3d-4830-9095-62bceed17123",
      "skill_id": "area_between_curves_dx_setup"
    },
    {
      "question_id": "6b7bb29a-de3d-4830-9095-62bceed17123",
      "skill_id": "solve_intersections_for_bounds"
    },
    {
      "question_id": "6bb7c325-f7c4-438f-b109-01de5e203065",
      "skill_id": "units_interpretation_in_applications"
    },
    {
      "question_id": "6bb7c325-f7c4-438f-b109-01de5e203065",
      "skill_id": "integration_modeling_from_context"
    },
    {
      "question_id": "6c28814b-a841-476c-826b-79f1bb72338b",
      "skill_id": "arc_length_derivative_and_sqrt"
    },
    {
      "question_id": "6c28814b-a841-476c-826b-79f1bb72338b",
      "skill_id": "arc_length_formula"
    },
    {
      "question_id": "709c4140-d2ea-43ba-bbb5-f3adf368ec13",
      "skill_id": "solve_intersections_for_bounds"
    },
    {
      "question_id": "709c4140-d2ea-43ba-bbb5-f3adf368ec13",
      "skill_id": "area_multiple_intersections_split"
    },
    {
      "question_id": "73fc26d0-de90-4ffd-8ff8-b7dedccf0ae9",
      "skill_id": "washer_shift_radius_adjustment"
    },
    {
      "question_id": "73fc26d0-de90-4ffd-8ff8-b7dedccf0ae9",
      "skill_id": "numerical_approx_trapezoid_volume"
    },
    {
      "question_id": "8429180f-c1e6-48d2-932f-a3b88eea96b6",
      "skill_id": "axis_shift_handling"
    },
    {
      "question_id": "8429180f-c1e6-48d2-932f-a3b88eea96b6",
      "skill_id": "choose_dx_or_dy_strategy_volume"
    },
    {
      "question_id": "86837242-90a3-4798-9437-be1a6f837518",
      "skill_id": "cross_section_area_function"
    },
    {
      "question_id": "86837242-90a3-4798-9437-be1a6f837518",
      "skill_id": "bounds_from_context"
    },
    {
      "question_id": "87bb0416-c251-46f0-8a1e-a02e9ada217d",
      "skill_id": "motion_displacement_from_velocity"
    },
    {
      "question_id": "87bb0416-c251-46f0-8a1e-a02e9ada217d",
      "skill_id": "bounds_from_context"
    },
    {
      "question_id": "88cd43fc-e772-4cde-8771-29d3228fd517",
      "skill_id": "disk_method_bounds"
    },
    {
      "question_id": "88cd43fc-e772-4cde-8771-29d3228fd517",
      "skill_id": "disk_method_radius_expression"
    },
    {
      "question_id": "8b4545b5-6796-4b46-aaa6-a0861f15f762",
      "skill_id": "volume_disk_method_basic"
    },
    {
      "question_id": "8b4545b5-6796-4b46-aaa6-a0861f15f762",
      "skill_id": "radius_distance_to_axis"
    },
    {
      "question_id": "8dc2bf96-8dc5-46e3-8248-80395a37273b",
      "skill_id": "average_value_interpretation"
    },
    {
      "question_id": "8dc2bf96-8dc5-46e3-8248-80395a37273b",
      "skill_id": "average_value_formula"
    },
    {
      "question_id": "8ecbf18e-f7d8-4bd1-a813-36872f5c9367",
      "skill_id": "radius_distance_to_axis"
    },
    {
      "question_id": "8ecbf18e-f7d8-4bd1-a813-36872f5c9367",
      "skill_id": "volume_revolution_about_shifted_axis"
    },
    {
      "question_id": "92dc088a-1f90-4f0e-ac26-79d44bcf8829",
      "skill_id": "volume_revolution_about_x_or_y"
    },
    {
      "question_id": "92dc088a-1f90-4f0e-ac26-79d44bcf8829",
      "skill_id": "bounds_from_context"
    },
    {
      "question_id": "9585041c-4ca3-4e3f-aceb-5988630a190e",
      "skill_id": "accumulation_from_rate"
    },
    {
      "question_id": "9585041c-4ca3-4e3f-aceb-5988630a190e",
      "skill_id": "bounds_from_context"
    },
    {
      "question_id": "96138cdc-b2b2-4f5e-b04e-50c283db5e65",
      "skill_id": "arc_length_formula_setup"
    },
    {
      "question_id": "96138cdc-b2b2-4f5e-b04e-50c283db5e65",
      "skill_id": "arc_length_derivative_needed"
    },
    {
      "question_id": "98554787-e879-4f8c-a643-94dd8e4875bd",
      "skill_id": "area_between_curves_dy_setup"
    },
    {
      "question_id": "98554787-e879-4f8c-a643-94dd8e4875bd",
      "skill_id": "solve_intersections_for_bounds"
    },
    {
      "question_id": "9967eef0-6d9e-424f-a2ed-091ea53e0f43",
      "skill_id": "arc_length_units_interpretation"
    },
    {
      "question_id": "9967eef0-6d9e-424f-a2ed-091ea53e0f43",
      "skill_id": "distance_vs_displacement"
    },
    {
      "question_id": "99bbe365-98de-4892-b610-cf18278e527f",
      "skill_id": "choose_dx_or_dy_strategy_volume"
    },
    {
      "question_id": "99bbe365-98de-4892-b610-cf18278e527f",
      "skill_id": "volume_cross_sections_setup"
    },
    {
      "question_id": "a1f651c4-75de-4ba2-aa34-65e69faf54f8",
      "skill_id": "area_between_curves_dy_setup"
    },
    {
      "question_id": "a1f651c4-75de-4ba2-aa34-65e69faf54f8",
      "skill_id": "choose_dx_or_dy_strategy_area"
    },
    {
      "question_id": "a5266a5e-801a-42eb-b4a8-035d81680c60",
      "skill_id": "cross_sections_square"
    },
    {
      "question_id": "a5266a5e-801a-42eb-b4a8-035d81680c60",
      "skill_id": "cross_section_area_function"
    },
    {
      "question_id": "a7018ceb-3cad-4609-9972-38ca922657a9",
      "skill_id": "area_between_curves_dx_setup"
    },
    {
      "question_id": "a7018ceb-3cad-4609-9972-38ca922657a9",
      "skill_id": "solve_intersections_for_bounds"
    },
    {
      "question_id": "a7c27dfd-4986-4ee5-9278-6b3221965db9",
      "skill_id": "numerical_approx_trapezoid_volume"
    },
    {
      "question_id": "a7c27dfd-4986-4ee5-9278-6b3221965db9",
      "skill_id": "cross_section_semicircle_area"
    },
    {
      "question_id": "b2d3bb71-074f-4c5c-b345-1d137f262c02",
      "skill_id": "area_top_minus_bottom_or_right_minus_left"
    },
    {
      "question_id": "b2d3bb71-074f-4c5c-b345-1d137f262c02",
      "skill_id": "solve_intersections_for_bounds"
    },
    {
      "question_id": "b5c1de91-9989-4018-899f-0bb60f2a46eb",
      "skill_id": "choose_dx_or_dy_strategy_volume"
    },
    {
      "question_id": "b5c1de91-9989-4018-899f-0bb60f2a46eb",
      "skill_id": "washer_method_setup"
    },
    {
      "question_id": "b70c8248-2a30-4756-8b84-0ea68ec97f26",
      "skill_id": "distance_vs_displacement"
    },
    {
      "question_id": "b70c8248-2a30-4756-8b84-0ea68ec97f26",
      "skill_id": "absolute_value_in_distance"
    },
    {
      "question_id": "bbdafb05-9f3f-4b9d-8962-10edf3438b1a",
      "skill_id": "units_interpretation_in_applications"
    },
    {
      "question_id": "bbdafb05-9f3f-4b9d-8962-10edf3438b1a",
      "skill_id": "accumulation_from_rate"
    },
    {
      "question_id": "bf2f23f3-cca4-4e41-82f6-1ca19597f176",
      "skill_id": "choose_dx_or_dy_strategy_area"
    },
    {
      "question_id": "bf2f23f3-cca4-4e41-82f6-1ca19597f176",
      "skill_id": "area_between_curves_dy_setup"
    },
    {
      "question_id": "c256c221-d33b-437e-b5b9-e9e5f9cfa85a",
      "skill_id": "method_selection_disk_vs_washer"
    },
    {
      "question_id": "c256c221-d33b-437e-b5b9-e9e5f9cfa85a",
      "skill_id": "axis_shift_handling"
    },
    {
      "question_id": "c3669987-04fa-4ec6-95dc-10fbc820f207",
      "skill_id": "total_distance_vs_displacement"
    },
    {
      "question_id": "c3669987-04fa-4ec6-95dc-10fbc820f207",
      "skill_id": "motion_displacement_from_velocity"
    },
    {
      "question_id": "c5cbcbe4-d2e7-4511-831a-14edc9073c7d",
      "skill_id": "volume_cross_sections_setup"
    },
    {
      "question_id": "c5cbcbe4-d2e7-4511-831a-14edc9073c7d",
      "skill_id": "cross_section_semicircle_area"
    },
    {
      "question_id": "c60cde02-5979-43df-a804-8d1240d029bd",
      "skill_id": "area_between_curves_dx_setup"
    },
    {
      "question_id": "c60cde02-5979-43df-a804-8d1240d029bd",
      "skill_id": "bounds_from_context"
    },
    {
      "question_id": "c61a6ca0-8f6b-4b08-abc2-b3ea89479a00",
      "skill_id": "area_multiple_intersections_split"
    },
    {
      "question_id": "c61a6ca0-8f6b-4b08-abc2-b3ea89479a00",
      "skill_id": "solve_intersections_for_bounds"
    },
    {
      "question_id": "c6474d52-305b-4c38-be47-c56f0451e44c",
      "skill_id": "axis_shift_handling"
    },
    {
      "question_id": "c6474d52-305b-4c38-be47-c56f0451e44c",
      "skill_id": "disk_shift_radius_adjustment"
    },
    {
      "question_id": "cbfc7bee-a1c8-44a0-9250-06fd686a8cfd",
      "skill_id": "motion_position_with_initial_condition"
    },
    {
      "question_id": "cbfc7bee-a1c8-44a0-9250-06fd686a8cfd",
      "skill_id": "motion_displacement_from_velocity"
    },
    {
      "question_id": "cc958eaa-b680-4f65-8610-90cbbc9a7976",
      "skill_id": "disk_shift_radius_adjustment"
    },
    {
      "question_id": "cc958eaa-b680-4f65-8610-90cbbc9a7976",
      "skill_id": "disk_method_evaluation"
    },
    {
      "question_id": "cd70d579-e02e-4b40-b8f4-94d6a4269f75",
      "skill_id": "volume_cross_sections_setup"
    },
    {
      "question_id": "cd70d579-e02e-4b40-b8f4-94d6a4269f75",
      "skill_id": "cross_section_square_area"
    },
    {
      "question_id": "d28d772a-f986-4e1c-9d43-eca1932375a2",
      "skill_id": "area_multiple_intersections_split"
    },
    {
      "question_id": "d28d772a-f986-4e1c-9d43-eca1932375a2",
      "skill_id": "area_top_minus_bottom_or_right_minus_left"
    },
    {
      "question_id": "d30dabf3-0395-41bf-a97f-e69a46e401af",
      "skill_id": "washer_method_setup"
    },
    {
      "question_id": "d30dabf3-0395-41bf-a97f-e69a46e401af",
      "skill_id": "washer_method_inner_outer_radius"
    },
    {
      "question_id": "d5f80928-0418-4ae8-ab5a-557330c547b0",
      "skill_id": "arc_length_formula"
    },
    {
      "question_id": "d5f80928-0418-4ae8-ab5a-557330c547b0",
      "skill_id": "arc_length_derivative_and_sqrt"
    },
    {
      "question_id": "dbc7fdf0-87a5-4611-ac9f-895147a576f4",
      "skill_id": "volume_cross_sections_setup"
    },
    {
      "question_id": "dbc7fdf0-87a5-4611-ac9f-895147a576f4",
      "skill_id": "cross_section_square_area"
    },
    {
      "question_id": "df17f9f8-3246-4d5d-b856-336ae493e0d4",
      "skill_id": "distance_from_velocity_graph"
    },
    {
      "question_id": "df17f9f8-3246-4d5d-b856-336ae493e0d4",
      "skill_id": "absolute_value_in_distance"
    },
    {
      "question_id": "e2aa6f5f-ec38-4946-b76f-126689ef1fde",
      "skill_id": "disk_method_radius_expression"
    },
    {
      "question_id": "e2aa6f5f-ec38-4946-b76f-126689ef1fde",
      "skill_id": "choose_dx_or_dy_strategy_volume"
    },
    {
      "question_id": "e509e60b-3f80-48a3-9147-b882295def64",
      "skill_id": "disk_shift_radius_adjustment"
    },
    {
      "question_id": "e509e60b-3f80-48a3-9147-b882295def64",
      "skill_id": "disk_method_setup"
    },
    {
      "question_id": "eeb274f9-c080-4af0-a682-a4762474cf90",
      "skill_id": "area_multiple_intersections_split"
    },
    {
      "question_id": "eeb274f9-c080-4af0-a682-a4762474cf90",
      "skill_id": "solve_intersections_for_bounds"
    },
    {
      "question_id": "f6999aff-67ac-4f9a-935a-f810e071630f",
      "skill_id": "cross_sections_semicircle"
    },
    {
      "question_id": "f6999aff-67ac-4f9a-935a-f810e071630f",
      "skill_id": "cross_section_area_function"
    },
    {
      "question_id": "f79aa212-a98d-46e3-b9c8-ac3bbfde36f4",
      "skill_id": "volume_integral_evaluation"
    },
    {
      "question_id": "f79aa212-a98d-46e3-b9c8-ac3bbfde36f4",
      "skill_id": "volume_cross_sections_setup"
    },
    {
      "question_id": "fa8b3065-6c60-4b7e-8c45-fa68fa79fcbf",
      "skill_id": "choose_dx_or_dy_strategy_volume"
    },
    {
      "question_id": "fa8b3065-6c60-4b7e-8c45-fa68fa79fcbf",
      "skill_id": "cross_section_rectangle_area"
    },
    {
      "question_id": "ffa716d6-6dfa-4e60-aef7-f7a2abad2420",
      "skill_id": "average_value_from_graph_or_table"
    },
    {
      "question_id": "ffa716d6-6dfa-4e60-aef7-f7a2abad2420",
      "skill_id": "average_value_formula"
    }
  ]
}